clear_dev/__init__.py
clear_dev/cli.py
clear_dev/gui.py
clear_dev/gui_app.py
clear_dev/package_scanner.py
clear_dev/scanner.py
clear_dev/windows_cleaner.py
clear_dev-1.0.1.dist-info/METADATA
clear_dev-1.0.1.dist-info/WHEEL
clear_dev-1.0.1.dist-info/entry_points.txt
clear_dev-1.0.1.dist-info/licenses/LICENSE
clear_dev-1.0.1.dist-info/RECORD
