Metadata-Version: 2.4
Name: clear-dev
Version: 1.0.1
Summary: A powerful development cache and directory scanner with GUI and CLI interfaces
Project-URL: Homepage, https://github.com/duolabmeng6/clear_dev
Project-URL: Repository, https://github.com/duolabmeng6/clear_dev
Project-URL: Documentation, https://github.com/duolabmeng6/clear_dev#readme
Project-URL: Bug Tracker, https://github.com/duolabmeng6/clear_dev/issues
Project-URL: Changelog, https://github.com/duolabmeng6/clear_dev/releases
Author-email: duolabmeng6 <duolabmeng6@gmail.com>
Maintainer-email: duolabmeng6 <duolabmeng6@gmail.com>
License: MIT
License-File: LICENSE
Keywords: build-cache,cache-cleaner,cli,development-tools,directory-scanner,disk-cleanup,gui,node-modules
Classifier: Development Status :: 5 - Production/Stable
Classifier: Environment :: Console
Classifier: Environment :: X11 Applications :: Qt
Classifier: Intended Audience :: Developers
Classifier: License :: OSI Approved :: MIT License
Classifier: Operating System :: OS Independent
Classifier: Programming Language :: Python :: 3
Classifier: Programming Language :: Python :: 3.8
Classifier: Programming Language :: Python :: 3.9
Classifier: Programming Language :: Python :: 3.10
Classifier: Programming Language :: Python :: 3.11
Classifier: Programming Language :: Python :: 3.12
Classifier: Programming Language :: Python :: 3.13
Classifier: Topic :: Software Development :: Build Tools
Classifier: Topic :: System :: Filesystems
Classifier: Topic :: Utilities
Requires-Python: >=3.8
Requires-Dist: pyside6>=6.6.3.1
Provides-Extra: all
Requires-Dist: pyside6>=6.5.0; extra == 'all'
Provides-Extra: gui
Requires-Dist: pyside6>=6.5.0; extra == 'gui'
